pydrantic/__init__.py
pydrantic/cli.py
pydrantic/config.py
pydrantic/parser.py
pydrantic/types.py
pydrantic/utils.py
pydrantic/variables.py
pydrantic-0.0.3.dist-info/licenses/LICENSE
pydrantic-0.0.3.dist-info/METADATA
pydrantic-0.0.3.dist-info/WHEEL
pydrantic-0.0.3.dist-info/top_level.txt
pydrantic-0.0.3.dist-info/RECORD
