Metadata-Version: 2.4
Name: pydrantic
Version: 0.0.3
Summary: A simple library that facilitates the use of Pydantic models for configuration
Home-page: https://github.com/seyuboglu/pydrantic
Author: Sabri Eyuboglu
Classifier: Development Status :: 3 - Alpha
Classifier: Intended Audience :: Developers
Classifier: Programming Language :: Python :: 3
Classifier: Programming Language :: Python :: 3.9
Classifier: Programming Language :: Python :: 3.10
Classifier: Programming Language :: Python :: 3.11
Classifier: Programming Language :: Python :: 3.12
Requires-Python: >=3.9
License-File: LICENSE
Requires-Dist: pyyaml<7,>=6.0
Requires-Dist: dill<0.4,>=0.3.7
Requires-Dist: pydantic>=2.9.2
Dynamic: author
Dynamic: classifier
Dynamic: description
Dynamic: description-content-type
Dynamic: home-page
Dynamic: license-file
Dynamic: requires-dist
Dynamic: requires-python
Dynamic: summary
